Metadata-Version: 1.0
Name: geekberry
Version: 1.0.6
Summary: Some tools.
Home-page: https://github.com/GeekBerry/geekberry
Author: GeekBerry
Author-email: GeekBerry@qq.com
License: MIT Licence
Keywords: pip,geekberry,database
Platform: any
